stix_shifter_modules/aws_security_hub/__init__.py
stix_shifter_modules/aws_security_hub/entry_point.py
stix_shifter_modules/aws_security_hub/stix_translation/__init__.py
stix_shifter_modules/aws_security_hub/stix_translation/query_constructor.py
stix_shifter_modules/aws_security_hub/stix_translation/query_translator.py
stix_shifter_modules/aws_security_hub/stix_translation/results_translator.py
stix_shifter_modules/aws_security_hub/stix_translation/json/from_stix_map.json
stix_shifter_modules/aws_security_hub/stix_translation/json/to_stix_map.json
stix_shifter_modules/aws_security_hub/stix_transmission/__init__.py
stix_shifter_modules/aws_security_hub/stix_transmission/connector.py
stix_shifter_modules_aws_security_hub-3.1.8.dist-info/LICENSE.md
stix_shifter_modules_aws_security_hub-3.1.8.dist-info/METADATA
stix_shifter_modules_aws_security_hub-3.1.8.dist-info/NOTICE
stix_shifter_modules_aws_security_hub-3.1.8.dist-info/WHEEL
stix_shifter_modules_aws_security_hub-3.1.8.dist-info/top_level.txt
stix_shifter_modules_aws_security_hub-3.1.8.dist-info/RECORD
